{
  "name": "NEXLAB",
  "version": "26.9.0",
  "revision": "agenda-lista-atual-correcoes-13-a-15-r25",
  "channel": "stable",
  "title": "Agenda — virada do dia, acessibilidade e limpeza de índices",
  "built_at": "2026-07-13T15:10:00Z",
  "requires_sql": false,
  "sql_migration": null,
  "new_sql_migration": null,
  "applied_migration": "agenda_lista_atual_correcoes_13_a_15_v26_9_0",
  "depends_on_migration": "agenda_lista_atual_correcoes_9_a_12_v26_9_0",
  "previous_revision": "agenda-lista-atual-correcoes-9-a-12-r24",
  "scope": "v26.9.0 — Agenda, correções finais 13 a 15; pacote exclusivo para GitHub Pages",
  "runtime": {
    "feedback_canonical_fields": true,
    "feedback_title_field": "titulo",
    "feedback_description_field": "descricao",
    "reservation_owner_field": "usuario_id",
    "reservation_legacy_owner_mirrored": true,
    "reservation_resources_persisted": true,
    "reservation_description_persisted": true,
    "reservation_room_persisted": true,
    "meeting_time_field": "hora",
    "meeting_time_alias": "horario",
    "meeting_online_link_persisted": true,
    "meeting_selected_participant_rls": true,
    "service_worker_cache": "nexlab-v26-9-0-shell-r25",
    "agenda_secure_rpc": true,
    "agenda_rpc_name": "nexlab_get_agenda_range_v2690",
    "agenda_direct_source_queries_removed": true,
    "agenda_minimal_reservation_fields": true,
    "agenda_task_only_project_mask": true,
    "agenda_task_only_private_description_blocked": true,
    "reservation_review_rpc": true,
    "reservation_review_rpc_name": "nexlab_review_reservation_v2690",
    "reservation_review_row_lock": true,
    "reservation_expected_status_guard": true,
    "reservation_rejection_reason_required": true,
    "reservation_past_approval_blocked": true,
    "reservation_decision_audited": true,
    "feedback_management_rpc": true,
    "feedback_management_rpc_name": "nexlab_manage_feedback_v2690",
    "feedback_management_row_lock": true,
    "feedback_expected_status_guard": true,
    "pending_meetings_removed": true,
    "pending_tasks_rpc": true,
    "pending_tasks_rpc_name": "nexlab_get_my_pending_tasks_v2690",
    "pending_task_completion_action": true,
    "pending_metrics_separated": true,
    "feedback_owner_canonicalization_deferred": false,
    "pending_center_rpc": true,
    "pending_center_rpc_name": "nexlab_get_pending_center_v2690",
    "pending_realtime": true,
    "pending_sidebar_count_realtime": true,
    "pending_partial_load_state": true,
    "pending_last_valid_state_preserved": true,
    "pending_pagination": true,
    "pending_page_size_per_source": 8,
    "pending_minimal_profiles": true,
    "pending_direct_profile_query_removed": true,
    "pending_accessible_filter_labels": true,
    "pending_accessible_profile_rejection_dialog": true,
    "pending_results_live_region": true,
    "pending_results_region": true,
    "feedback_duplicate_index_removed": true,
    "meeting_visibility_helper": true,
    "meeting_visibility_helper_name": "nexlab_can_view_meeting_v2690",
    "meeting_all_authorized_profiles": true,
    "meeting_origin_module_permission_required": true,
    "agenda_origin_module_permissions": true,
    "feedback_owner_field": "usuario_id",
    "feedback_legacy_owner_field": "autor_id",
    "feedback_legacy_owner_mirrored": true,
    "feedback_owner_sync_trigger": true,
    "agenda_future_items_datetime": true,
    "agenda_cancelled_meetings_filtered": true,
    "agenda_cancelled_meetings_status_and_timestamp": true,
    "agenda_closed_projects_filtered": true,
    "agenda_closed_marketing_filtered": true,
    "main_bundle_module_syntax_valid": true,
    "react_internal_queue_restored": true,
    "github_publication_package_only": true,
    "agenda_date_range_loading": true,
    "agenda_range_margin_days": 7,
    "agenda_max_rpc_range_days": 120,
    "agenda_contextual_conflicts": true,
    "agenda_conflict_pair_metric": true,
    "agenda_default_event_duration_minutes": 60,
    "agenda_default_meeting_duration_minutes": 60,
    "agenda_semantic_deduplication": true,
    "agenda_realtime": true,
    "agenda_realtime_debounce_ms": 450,
    "agenda_partial_load_state": true,
    "agenda_last_valid_state_preserved": true,
    "agenda_limited_view_notice": true,
    "agenda_source_status": true,
    "agenda_commitment_metadata": true,
    "agenda_direct_record_navigation": true,
    "agenda_exact_record_highlight": true,
    "agenda_midnight_rollover": true,
    "agenda_today_state_reactive": true,
    "agenda_midnight_reload": true,
    "agenda_accessible_search_label": true,
    "agenda_accessible_filter_labels": true,
    "agenda_filter_live_announcements": true,
    "agenda_results_region": true,
    "agenda_view_aria_pressed": true,
    "agenda_period_filter_aria_pressed": true,
    "agenda_abbreviations_decorative": true,
    "agenda_calendar_item_labels": true,
    "agenda_today_aria_current": true,
    "meeting_participants_duplicate_index_removed": true,
    "reservation_participants_duplicate_index_removed": true
  },
  "publication": {
    "replace_all_files": true,
    "clear_service_worker": true,
    "test_homologation": true,
    "supabase_migration_applied": true,
    "new_supabase_migration_required": false,
    "supabase_project": "Nexlab",
    "requires_sql": false
  },
  "remaining_project_corrections": 0,
  "remaining_team_corrections": 0,
  "remaining_dashboard_corrections": 0,
  "remaining_pendencias_agenda_review_points": 0,
  "changes": [
    "A Agenda recalcula automaticamente o dia atual, atrasos, próximos sete dias e itens futuros após a virada da meia-noite.",
    "Busca, filtros, visualizações, calendário e lista receberam rótulos, estados e regiões acessíveis.",
    "As abreviações dos tipos deixaram de ser anunciadas isoladamente por leitores de tela.",
    "Os índices únicos redundantes de participantes de reuniões e reservas foram removidos, mantendo as chaves primárias e índices de consulta por usuário."
  ],
  "applied_migrations": [
    "pendencias_agenda_correcoes_5_a_8_v26_9_0",
    "pendencias_agenda_reservation_audit_actions_v26_9_0",
    "pendencias_agenda_reservation_expected_status_guard_v26_9_0",
    "pendencias_agenda_correcoes_9_a_12_v26_9_0",
    "pendencias_agenda_correcoes_13_a_16_v26_9_0",
    "pendencias_agenda_correcoes_17_a_20_v26_9_0",
    "pendencias_agenda_lista_atual_correcoes_1_a_4_v26_9_0",
    "agenda_lista_atual_correcoes_5_a_8_v26_9_0",
    "agenda_lista_atual_correcoes_9_a_12_v26_9_0",
    "agenda_lista_atual_correcoes_13_a_15_v26_9_0"
  ]
}
