{
  "name": "NEXLAB",
  "version": "26.9.0",
  "revision": "publicacao-hotfix-tela-branca-r21",
  "channel": "stable",
  "title": "Correção crítica de publicação — tela branca",
  "built_at": "2026-07-13T13:24:59Z",
  "requires_sql": false,
  "sql_migration": null,
  "new_sql_migration": null,
  "applied_migration": "pendencias_agenda_lista_atual_correcoes_1_a_4_v26_9_0",
  "depends_on_migration": "pendencias_agenda_correcoes_17_a_20_v26_9_0",
  "previous_revision": "pendencias-agenda-lista-atual-correcoes-1-a-4-r20",
  "scope": "v26.9.0 — hotfix do bundle e pacote exclusivo para GitHub Pages",
  "runtime": {
    "feedback_canonical_fields": true,
    "feedback_title_field": "titulo",
    "feedback_description_field": "descricao",
    "reservation_owner_field": "usuario_id",
    "reservation_legacy_owner_mirrored": true,
    "reservation_resources_persisted": true,
    "reservation_description_persisted": true,
    "reservation_room_persisted": true,
    "meeting_time_field": "hora",
    "meeting_time_alias": "horario",
    "meeting_online_link_persisted": true,
    "meeting_selected_participant_rls": true,
    "service_worker_cache": "nexlab-v26-9-0-shell-r21",
    "agenda_secure_rpc": true,
    "agenda_rpc_name": "nexlab_get_agenda_summary_v2690",
    "agenda_direct_source_queries_removed": true,
    "agenda_minimal_reservation_fields": true,
    "agenda_task_only_project_mask": true,
    "agenda_task_only_private_description_blocked": true,
    "reservation_review_rpc": true,
    "reservation_review_rpc_name": "nexlab_review_reservation_v2690",
    "reservation_review_row_lock": true,
    "reservation_expected_status_guard": true,
    "reservation_rejection_reason_required": true,
    "reservation_past_approval_blocked": true,
    "reservation_decision_audited": true,
    "feedback_management_rpc": true,
    "feedback_management_rpc_name": "nexlab_manage_feedback_v2690",
    "feedback_management_row_lock": true,
    "feedback_expected_status_guard": true,
    "pending_meetings_removed": true,
    "pending_tasks_rpc": true,
    "pending_tasks_rpc_name": "nexlab_get_my_pending_tasks_v2690",
    "pending_task_completion_action": true,
    "pending_metrics_separated": true,
    "feedback_owner_canonicalization_deferred": false,
    "pending_center_rpc": true,
    "pending_center_rpc_name": "nexlab_get_pending_center_v2690",
    "pending_realtime": true,
    "pending_sidebar_count_realtime": true,
    "pending_partial_load_state": true,
    "pending_last_valid_state_preserved": true,
    "pending_pagination": true,
    "pending_page_size_per_source": 8,
    "pending_minimal_profiles": true,
    "pending_direct_profile_query_removed": true,
    "pending_accessible_filter_labels": true,
    "pending_accessible_profile_rejection_dialog": true,
    "pending_results_live_region": true,
    "pending_results_region": true,
    "feedback_duplicate_index_removed": true,
    "meeting_visibility_helper": true,
    "meeting_visibility_helper_name": "nexlab_can_view_meeting_v2690",
    "meeting_all_authorized_profiles": true,
    "meeting_origin_module_permission_required": true,
    "agenda_origin_module_permissions": true,
    "feedback_owner_field": "usuario_id",
    "feedback_legacy_owner_field": "autor_id",
    "feedback_legacy_owner_mirrored": true,
    "feedback_owner_sync_trigger": true,
    "agenda_future_items_datetime": true,
    "agenda_cancelled_meetings_filtered": true,
    "agenda_cancelled_meetings_status_and_timestamp": true,
    "agenda_closed_projects_filtered": true,
    "agenda_closed_marketing_filtered": true,
    "main_bundle_module_syntax_valid": true,
    "react_internal_queue_restored": true,
    "github_publication_package_only": true
  },
  "publication": {
    "replace_all_files": false,
    "clear_service_worker": true,
    "test_homologation": true,
    "supabase_migration_applied": true,
    "new_supabase_migration_required": true,
    "supabase_project": "Nexlab"
  },
  "remaining_project_corrections": 0,
  "remaining_team_corrections": 0,
  "remaining_dashboard_corrections": 0,
  "remaining_pendencias_agenda_review_points": 11,
  "changes": [
    "Corrigida colisão do identificador bo que impedia o bundle ES module de ser interpretado.",
    "Restaurada a função interna do React sobrescrita acidentalmente por um helper de logs.",
    "Pacote de publicação passa a conter somente arquivos estáticos destinados ao GitHub.",
    "Nenhuma migration adicional é necessária para este hotfix."
  ],
  "applied_migrations": [
    "pendencias_agenda_correcoes_5_a_8_v26_9_0",
    "pendencias_agenda_reservation_audit_actions_v26_9_0",
    "pendencias_agenda_reservation_expected_status_guard_v26_9_0",
    "pendencias_agenda_correcoes_9_a_12_v26_9_0",
    "pendencias_agenda_correcoes_13_a_16_v26_9_0",
    "pendencias_agenda_correcoes_17_a_20_v26_9_0",
    "pendencias_agenda_lista_atual_correcoes_1_a_4_v26_9_0"
  ]
}
